pynintendoauth/__init__.py
pynintendoauth/_version.py
pynintendoauth/const.py
pynintendoauth/exceptions.py
pynintendoauth/utils.py
pynintendoauth-1.0.2.dist-info/licenses/LICENSE
pynintendoauth-1.0.2.dist-info/METADATA
pynintendoauth-1.0.2.dist-info/WHEEL
pynintendoauth-1.0.2.dist-info/top_level.txt
pynintendoauth-1.0.2.dist-info/RECORD
